trimeshtools/__init__.py
trimeshtools/axis.py
trimeshtools/combine.py
trimeshtools/deform.py
trimeshtools/edit.py
trimeshtools/figures.py
trimeshtools/move.py
trimeshtools/rotate.py
trimeshtools/show.py
trimeshtools/surface.py
trimeshtools/utils.py
trimeshtools-0.1.5.dist-info/licenses/LICENSE
trimeshtools-0.1.5.dist-info/METADATA
trimeshtools-0.1.5.dist-info/WHEEL
trimeshtools-0.1.5.dist-info/top_level.txt
trimeshtools-0.1.5.dist-info/RECORD
